Workbook

Sheet Total_Bank
A1: Bank | B1: Total Assets FY25 ($M CAD) | C1: Total Revenue FY25 ($M) | D1: Total Revenue FY24 ($M) | E1: Net Income FY25 ($M) | F1: Net Income FY24 ($M) | G1: Source File | H1: Notes
A2: RBC | B2: 2325006 | C2: 66605 | D2: 57344 | E2: 20369 | F2: 16240 | G2: Annual_Report_2025_e.pdf | H2: Fiscal year ended Oct 31, 2025
A3: TD | B3: 2094600 | C3: 67777 | D3: 57223 | E3: 20538 | F3: 8842 | G3: 2025-annual-report-en_Updated.pdf | H3: FY24 net income reflects one-off items (BSA/AML charge); FY25 includes Schwab sale gain
A4: BMO | B4: 1580221 | C4: 36274 | D4: 32795 | E4: 8725 | F4: 7327 | G4: 2025_Annual_Report_English_SEDAR_Dec_16.pdf | H4: 208th Annual Report
A5: CIBC | B5: 1116938 | C5: 29133 | D5: 25606 | E5: 8454 | F5: 7154 | G5: CIBC_2025_Annual_Report_en.pdf
A6: Scotiabank (BNS) | B6: 1460042 | C6: 37741 | D6: 33670 | E6: 7758 | F6: 8491 | G6: BNS_AR25_Eng.pdf | H6: Reported basis; bank also discloses an 'Adjusted' basis with revenue $37,731M
A7: National Bank | B7: 576919 | C7: 13980 | D7: 11400 | E7: 4017 | F7: 3816 | G7: 2025_Annual_Report_Eng.pdf | H7: Total assets up 25% YoY, driven by CWB (Canadian Western Bank) acquisition

Sheet README
A1: Column1 | B1: Column2
A2: Raw_Bank_Financials — Big Six FY2025 Annual Report Data
A3: All figures FY2025 (year ended Oct 31, 2025) unless noted. Source: each bank's FY2025 Annual Report (as uploaded).
A5: Tab: Total_Bank | B5: Whole-bank figures — total assets, total revenue, net income. Sizing/context reference.
A6: Tab: PC_Segment | B6: The retail/commercial segment exposed to open banking disruption. Segment names differ by bank (see Notes column) but all represent Canadian personal + commercial/business banking.
A7: Tab: Fee_Breakout | B7: Card/payment/service-charge fee detail where disclosed. This is your best proxy for 'revenue at risk' from fintech disintermediation — not all banks disclose this at the same granularity.
A8: Segment naming caveat | B8: RBC reports 'Personal Banking' and 'Commercial Banking' as SEPARATE segments (not combined P&C like the other five banks). For an apples-to-apples P&C comparison, sum RBC's Personal Banking + Commercial Banking net income.
A9: BMO fiscal note | B9: BMO segment table labelled 'Canadian P&C' includes both Personal & Business Banking and Commercial Banking lines of business combined.

Sheet Raw_Canada_Baseline
A1: Metric | B1: Value | C1: Unit | D1: As-Of Date | E1: Months Since Launch | F1: Date Retrieved | G1: Source Name | H1: URL | I1: Status | J1: Notes
A2: Screen-scraping user base (at-risk population) | B2: 9000000 | C2: people | D2: 2025 (Dept. of Finance estimate) | E2: =IFERROR(DATEDIF(Launch_Dates!$B$5,IF(ISNUMBER(D2),D2,IF(LEN(TRIM(D2))=4,DATE(VALUE(TRIM(D2)),1,1),DATEVALUE(D2))),"m"),"") | F2: 46213 | G2: DLA Piper / Dept. of Finance | H2: https://www.dlapiper.com/en-pl/insights/publications/2026/04/the-new-consumer-driven-banking-act-explained | I2: Pulled | J2: Baseline population that CDBA is designed to migrate to secure APIs; use as denominator for Canada adoption forecast
A3: CDBA Royal Assent date | B3: 2026-03-26 | C3: date | D3: 2026-03-26 | E3: =IFERROR(DATEDIF(Launch_Dates!$B$5,IF(ISNUMBER(D3),D3,IF(LEN(TRIM(D3))=4,DATE(VALUE(TRIM(D3)),1,1),DATEVALUE(D3))),"m"),"") -> 2 | F3: 46213 | G3: DLA Piper | H3: https://www.dlapiper.com/en-pl/insights/publications/2026/04/the-new-consumer-driven-banking-act-explained | I3: Pulled | J3: Bill C-15; establishes the Consumer-Driven Banking Act
A4: Phase 1 (read access) target | B4: 2026 | C4: year | D4: 2026 | E4: =IFERROR(DATEDIF(Launch_Dates!$B$5,IF(ISNUMBER(D4),D4,IF(LEN(TRIM(D4))=4,DATE(VALUE(TRIM(D4)),1,1),DATEVALUE(D4))),"m"),"") -> 0 | F4: 46213 | G4: Open Banking Tracker | H4: https://www.openbankingtracker.com/blog/open-banking-canada-what-is-coming-in-2026-and-2027 | I4: Needs Verification | J4: Exact date not yet confirmed by Bank of Canada as of March 2026
A5: Phase 2 (write access/payments) target | B5: 2027-mid | C5: date | D5: mid-2027 | E5: =IFERROR(DATEDIF(Launch_Dates!$B$5,IF(ISNUMBER(D5),D5,IF(LEN(TRIM(D5))=4,DATE(VALUE(TRIM(D5)),1,1),DATEVALUE(D5))),"m"),"") | F5: 46213 | G5: Open Banking Tracker / DLA Piper | H5: https://www.openbankingtracker.com/blog/open-banking-canada-what-is-coming-in-2026-and-2027 | I5: Pulled | J5: Contingent on Real-Time Rail being live and in widespread use
A6: Implementation budget (Bank of Canada) | B6: 19300000 | C6: CAD | D6: Budget 2025 | E6: =IFERROR(DATEDIF(Launch_Dates!$B$5,IF(ISNUMBER(D6),D6,IF(LEN(TRIM(D6))=4,DATE(VALUE(TRIM(D6)),1,1),DATEVALUE(D6))),"m"),"") | F6: 46213 | G6: Open Banking Tracker | H6: https://www.openbankingtracker.com/blog/open-banking-canada-what-is-coming-in-2026-and-2027 | I6: Pulled | J6: Over 2 years; ~CAD 5M/year admin cost thereafter
A7: Est. consumer savings from data portability (insurance analogy) | B7: 1.1-3.8 billion | C7: CAD/year | D7: Competition Bureau research | E7: =IFERROR(DATEDIF(Launch_Dates!$B$5,IF(ISNUMBER(D7),D7,IF(LEN(TRIM(D7))=4,DATE(VALUE(TRIM(D7)),1,1),DATEVALUE(D7))),"m"),"") | F7: 46213 | G7: Open Banking Tracker (citing Competition Bureau) | H7: https://www.openbankingtracker.com/blog/open-banking-canada-what-is-coming-in-2026-and-2027 | I7: Pulled | J7: Used as an analogy/proxy - not a direct open-banking-in-banking estimate
A8: Cor.Connect joint venture (TD/RBC/BMO) | B8: Qualitative flag | C8: entity | D8: ongoing | E8: =IFERROR(DATEDIF(Launch_Dates!$B$5,IF(ISNUMBER(D8),D8,IF(LEN(TRIM(D8))=4,DATE(VALUE(TRIM(D8)),1,1),DATEVALUE(D8))),"m"),"") | F8: 46213 | G8: The Logic | H8: https://thelogic.co/news/exclusive/symcor-open-banking-software/ | I8: Pulled | J8: Platform controlling how open banking data flows to third parties; testing since summer 2023; fintechs lobbying against exclusivity. Relevant to Phase 5 (competitive/strategic layer)

Sheet PC_Segment
A1: Bank | B1: Segment Name (as reported) | C1: Segment NII FY25 ($M) | D1: Segment Non-Interest Income FY25 ($M) | E1: Segment Total Revenue FY25 ($M) | F1: Segment Total Revenue FY24 ($M) | G1: Segment Net Income FY25 ($M) | H1: Segment Net Income FY24 ($M) | I1: % of Total Bank Net Income | J1: Notes
A2: RBC | B2: Personal Banking | E2: 19900 | G2: 7105 | H2: 5921 | J2: 94% of revenue from Canada, 6% Caribbean & U.S. NII/Non-II split not separately disclosed at segment level. ~15M Canadian clients. Add RBC 'Commercial Banking' (net income $3,020M FY25) for a full P&C-equivalent view.
A3: TD | B3: Canadian Personal and Commercial Banking | C3: 16701 | D3: 3985 | E3: 20686 | F3: 19790 | G3: 7317 | H3: 7219 | J3: 1,051 Canadian retail branches at period end
A4: BMO | B4: Canadian P&C | C4: 9667 | D4: 2595 | E4: 12262 | F4: 11439 | G4: 3295 | H4: 3457 | J4: Combines Personal & Business Banking + Commercial Banking lines of business
A5: CIBC | B5: Canadian Personal and Business Banking | E5: 12000 | F5: 10900 | G5: 3107 | H5: 2905 | J5: Revenue rounded to nearest $0.1B as disclosed (chart format); NII/Non-II split not separately broken out in MD&A summary
A6: Scotiabank (BNS) | B6: Canadian Banking | C6: 10484 | D6: 2941 | E6: 13425 | F6: 13033 | G6: 3425 | H6: 3777 | J6: Reported basis (bank also discloses Adjusted basis with near-identical figures)
A7: National Bank | B7: Personal and Commercial | E7: 5551 | G7: 1111 | J7: Serves ~3M individuals and 173,000+ businesses. Revenue mix: Retail 50%, Commercial Banking 38%, Payment Solutions 9%, Insurance 3%

Sheet Fee_Breakout
A1: Bank | B1: Fee Category | C1: FY25 ($M) | D1: FY24 ($M) | E1: Scope | F1: Notes
A2: RBC | B2: Service charges | C2: 2425 | D2: 2294 | E2: Total bank | F2: Not broken out by segment in MD&A summary; best available granularity
A3: RBC | B3: Card service revenue | C3: 1333 | D3: 1273 | E3: Total bank | F3: Interchange revenue + annual card fees
A4: National Bank | B4: Payment Solutions (% of P&C segment revenue) | C4: 9% (~$500) | D4: 11% (2024 %) | E4: Personal & Commercial segment only | F4: Estimated $ = 9% x $5,551M segment revenue. Best segment-level payments figure found across all six banks
A5: National Bank | B5: Retail (% of P&C segment revenue) | C5: 50% | D5: 41% (2024) | E5: Personal & Commercial segment only | F5: Retail banking share of segment revenue
A6: TD, BMO, CIBC, Scotiabank | B6: Card/payment fee detail | C6: Not separately disclosed | D6: - | E6: - | F6: These four banks did not break out card/payment fee revenue at the granularity RBC and National Bank did, in the sections reviewed. Check the Notes to Consolidated Financial Statements (search 'Non-Interest Income' as a note heading) for a more granular breakdown if needed for the model.

Sheet Country Comparison
A1: Column1 | B1: Column2 | C1: Column3 | D1: Column4 | E1: Column5
A2: Country | B2: Open Banking Users / Stat | C2: As-Of Date | D2: Notes | E2: Source
A3: UK | B3: 13.3 million active users (up from 1 million in 2020) | C3: 2025-03 | D3: Not an EU member post-Brexit but retained PSD2-derived Open Banking Standard; use as external mandated-regime benchmark | E3: Noda (citing Yapily/OBL report)
A4: Germany | B4: Ranked 2nd in EU adoption per Yapily 2025 report | C4: 2025 | D4: Exact user count not yet sourced - follow up | E4: Noda (citing Yapily)
A5: Sweden | B5: Highest penetration rate forecast in EU by 2027 (Forrester) | C5: 2027 (forecast) | D5: Penetration rate, not raw user count | E5: Kontomatik (citing Forrester)
A6: France | B6: Ranked in top 4 EU adoption per Yapily 2025 report | C6: 2025 | D6: Exact user count not yet sourced - follow up | E6: Noda (citing Yapily)

Sheet Calc_Adoption_Forecast
A1: Months | B1: UK API Calls (actual) | C1: UK MoM Growth % | D1: Canada Month | E1: Canada — Conservative | F1: Canada — Base | G1: Canada — Optimistic | H1: Cons. as % of 9M | I1: Base as % of 9M | J1: Opt. as % of 9M | L1: Column1 | M1: Column2 | N1: Column3
A2: ='Raw_UK_API_Data'!A2 -> 45413 | B2: ='Raw_UK_API_Data'!C2 -> 1520925954 | D2: Month 0 | E2: ='Raw_Canada_Baseline'!$B$2*0.05 -> 450000 | F2: ='Raw_Canada_Baseline'!$B$2*0.05 -> 450000 | G2: ='Raw_Canada_Baseline'!$B$2*0.05 -> 450000 | L2: Average of % growth by UK | M2: =AVERAGE(C3:C26) -> 0.025205712
A3: ='Raw_UK_API_Data'!A3 -> 45444 | B3: ='Raw_UK_API_Data'!C3 -> 1494386712 | C3: =IFERROR((B3/B2)-1,"") -> -0.017449398 | D3: Month 1 | E3: =MIN(E2*(1+$M$3),'Raw_Canada_Baseline'!$B$2) -> 457939.8 | F3: =MIN(F2*(1+$M$4),'Raw_Canada_Baseline'!$B$2) -> 461342.57 | G3: =MIN(G2*(1+$M$5),'Raw_Canada_Baseline'!$B$2) -> 464745.34 | H3: =E3/'Raw_Canada_Baseline'!$B$2 -> 0.0508822 | I3: =F3/'Raw_Canada_Baseline'!$B$2 -> 0.051260286 | J3: =G3/'Raw_Canada_Baseline'!$B$2 -> 0.051638371 | L3: Conservative | M3: =M2*0.7 -> 0.017643998 | N3: Canada grows 70% as fast — US-style slower adoption
A4: ='Raw_UK_API_Data'!A4 -> 45474 | B4: ='Raw_UK_API_Data'!C4 -> 1564131601 | C4: =IFERROR((B4/B3)-1,"") -> 0.046671245 | D4: Month 2 | E4: =MIN(E3*(1+$M$3),'Raw_Canada_Baseline'!$B$2) -> 466019.69 | F4: =MIN(F3*(1+$M$4),'Raw_Canada_Baseline'!$B$2) -> 472971.04 | G4: =MIN(G3*(1+$M$5),'Raw_Canada_Baseline'!$B$2) -> 479973.85 | H4: =E4/'Raw_Canada_Baseline'!$B$2 -> 0.051779965 | I4: =F4/'Raw_Canada_Baseline'!$B$2 -> 0.052552338 | J4: =G4/'Raw_Canada_Baseline'!$B$2 -> 0.053330428 | L4: Base | M4: =M2*1 -> 0.025205712 | N4: Canada tracks UK's pace — both are mandated regimes
A5: ='Raw_UK_API_Data'!A5 -> 45505 | B5: ='Raw_UK_API_Data'!C5 -> 1581848583 | C5: =IFERROR((B5/B4)-1,"") -> 0.011327041 | D5: Month 3 | E5: =MIN(E4*(1+$M$3),'Raw_Canada_Baseline'!$B$2) -> 474242.14 | F5: =MIN(F4*(1+$M$4),'Raw_Canada_Baseline'!$B$2) -> 484892.61 | G5: =MIN(G4*(1+$M$5),'Raw_Canada_Baseline'!$B$2) -> 495701.36 | H5: =E5/'Raw_Canada_Baseline'!$B$2 -> 0.052693571 | I5: =F5/'Raw_Canada_Baseline'!$B$2 -> 0.053876957 | J5: =G5/'Raw_Canada_Baseline'!$B$2 -> 0.055077929 | L5: Optimistic | M5: =M2*1.3 -> 0.032767426 | N5: Canada grows faster — starts with 9M people already primed via screen-scraping, unlike UK's cold start
A6: ='Raw_UK_API_Data'!A6 -> 45536 | B6: ='Raw_UK_API_Data'!C6 -> 1603209493 | C6: =IFERROR((B6/B5)-1,"") -> 0.013503764 | D6: Month 4 | E6: =MIN(E5*(1+$M$3),'Raw_Canada_Baseline'!$B$2) -> 482609.67 | F6: =MIN(F5*(1+$M$4),'Raw_Canada_Baseline'!$B$2) -> 497114.67 | G6: =MIN(G5*(1+$M$5),'Raw_Canada_Baseline'!$B$2) -> 511944.21 | H6: =E6/'Raw_Canada_Baseline'!$B$2 -> 0.053623296 | I6: =F6/'Raw_Canada_Baseline'!$B$2 -> 0.055234964 | J6: =G6/'Raw_Canada_Baseline'!$B$2 -> 0.056882691
A7: ='Raw_UK_API_Data'!A7 -> 45566 | B7: ='Raw_UK_API_Data'!C7 -> 1747365142 | C7: =IFERROR((B7/B6)-1,"") -> 0.089916913 | D7: Month 5 | E7: =MIN(E6*(1+$M$3),'Raw_Canada_Baseline'!$B$2) -> 491124.83 | F7: =MIN(F6*(1+$M$4),'Raw_Canada_Baseline'!$B$2) -> 509644.8 | G7: =MIN(G6*(1+$M$5),'Raw_Canada_Baseline'!$B$2) -> 528719.31 | H7: =E7/'Raw_Canada_Baseline'!$B$2 -> 0.054569426 | I7: =F7/'Raw_Canada_Baseline'!$B$2 -> 0.0566272 | J7: =G7/'Raw_Canada_Baseline'!$B$2 -> 0.05874659
A8: ='Raw_UK_API_Data'!A8 -> 45597 | B8: ='Raw_UK_API_Data'!C8 -> 1747874987 | C8: =IFERROR((B8/B7)-1,"") -> 0.00029177931 | D8: Month 6 | E8: =MIN(E7*(1+$M$3),'Raw_Canada_Baseline'!$B$2) -> 499790.24 | F8: =MIN(F7*(1+$M$4),'Raw_Canada_Baseline'!$B$2) -> 522490.76 | G8: =MIN(G7*(1+$M$5),'Raw_Canada_Baseline'!$B$2) -> 546044.08 | H8: =E8/'Raw_Canada_Baseline'!$B$2 -> 0.055532249 | I8: =F8/'Raw_Canada_Baseline'!$B$2 -> 0.058054529 | J8: =G8/'Raw_Canada_Baseline'!$B$2 -> 0.060671564
A9: ='Raw_UK_API_Data'!A9 -> 45627 | B9: ='Raw_UK_API_Data'!C9 -> 1853825146 | C9: =IFERROR((B9/B8)-1,"") -> 0.060616554 | D9: Month 7 | E9: =MIN(E8*(1+$M$3),'Raw_Canada_Baseline'!$B$2) -> 508608.53 | F9: =MIN(F8*(1+$M$4),'Raw_Canada_Baseline'!$B$2) -> 535660.52 | G9: =MIN(G8*(1+$M$5),'Raw_Canada_Baseline'!$B$2) -> 563936.54 | H9: =E9/'Raw_Canada_Baseline'!$B$2 -> 0.056512059 | I9: =F9/'Raw_Canada_Baseline'!$B$2 -> 0.059517835 | J9: =G9/'Raw_Canada_Baseline'!$B$2 -> 0.062659615
A10: ='Raw_UK_API_Data'!A10 -> 45658 | B10: ='Raw_UK_API_Data'!C10 -> 1909058414 | C10: =IFERROR((B10/B9)-1,"") -> 0.029794217 | D10: Month 8 | E10: =MIN(E9*(1+$M$3),'Raw_Canada_Baseline'!$B$2) -> 517582.42 | F10: =MIN(F9*(1+$M$4),'Raw_Canada_Baseline'!$B$2) -> 549162.22 | G10: =MIN(G9*(1+$M$5),'Raw_Canada_Baseline'!$B$2) -> 582415.29 | H10: =E10/'Raw_Canada_Baseline'!$B$2 -> 0.057509158 | I10: =F10/'Raw_Canada_Baseline'!$B$2 -> 0.061018024 | J10: =G10/'Raw_Canada_Baseline'!$B$2 -> 0.06471281
A11: ='Raw_UK_API_Data'!A11 -> 45689 | B11: ='Raw_UK_API_Data'!C11 -> 1780842248 | C11: =IFERROR((B11/B10)-1,"") -> -0.067161992 | D11: Month 9 | E11: =MIN(E10*(1+$M$3),'Raw_Canada_Baseline'!$B$2) -> 526714.65 | F11: =MIN(F10*(1+$M$4),'Raw_Canada_Baseline'!$B$2) -> 563004.24 | G11: =MIN(G10*(1+$M$5),'Raw_Canada_Baseline'!$B$2) -> 601499.54 | H11: =E11/'Raw_Canada_Baseline'!$B$2 -> 0.05852385 | I11: =F11/'Raw_Canada_Baseline'!$B$2 -> 0.062556027 | J11: =G11/'Raw_Canada_Baseline'!$B$2 -> 0.066833282
A12: ='Raw_UK_API_Data'!A12 -> 45717 | B12: ='Raw_UK_API_Data'!C12 -> 1990052545 | C12: =IFERROR((B12/B11)-1,"") -> 0.11747829 | D12: Month 10 | E12: =MIN(E11*(1+$M$3),'Raw_Canada_Baseline'!$B$2) -> 536008 | F12: =MIN(F11*(1+$M$4),'Raw_Canada_Baseline'!$B$2) -> 577195.17 | G12: =MIN(G11*(1+$M$5),'Raw_Canada_Baseline'!$B$2) -> 621209.13 | H12: =E12/'Raw_Canada_Baseline'!$B$2 -> 0.059556444 | I12: =F12/'Raw_Canada_Baseline'!$B$2 -> 0.064132796 | J12: =G12/'Raw_Canada_Baseline'!$B$2 -> 0.069023236
A13: ='Raw_UK_API_Data'!A13 -> 45748 | B13: ='Raw_UK_API_Data'!C13 -> 1952040978 | C13: =IFERROR((B13/B12)-1,"") -> -0.019100786 | D13: Month 11 | E13: =MIN(E12*(1+$M$3),'Raw_Canada_Baseline'!$B$2) -> 545465.32 | F13: =MIN(F12*(1+$M$4),'Raw_Canada_Baseline'!$B$2) -> 591743.78 | G13: =MIN(G12*(1+$M$5),'Raw_Canada_Baseline'!$B$2) -> 641564.55 | H13: =E13/'Raw_Canada_Baseline'!$B$2 -> 0.060607258 | I13: =F13/'Raw_Canada_Baseline'!$B$2 -> 0.065749309 | J13: =G13/'Raw_Canada_Baseline'!$B$2 -> 0.07128495
A14: ='Raw_UK_API_Data'!A14 -> 45778 | B14: ='Raw_UK_API_Data'!C14 -> 1998627582 | C14: =IFERROR((B14/B13)-1,"") -> 0.023865587 | D14: Month 12 | E14: =MIN(E13*(1+$M$3),'Raw_Canada_Baseline'!$B$2) -> 555089.51 | F14: =MIN(F13*(1+$M$4),'Raw_Canada_Baseline'!$B$2) -> 606659.11 | G14: =MIN(G13*(1+$M$5),'Raw_Canada_Baseline'!$B$2) -> 662586.97 | H14: =E14/'Raw_Canada_Baseline'!$B$2 -> 0.061676613 | I14: =F14/'Raw_Canada_Baseline'!$B$2 -> 0.067406567 | J14: =G14/'Raw_Canada_Baseline'!$B$2 -> 0.073620775
A15: ='Raw_UK_API_Data'!A15 -> 45809 | B15: ='Raw_UK_API_Data'!C15 -> 1971558351 | C15: =IFERROR((B15/B14)-1,"") -> -0.013543909 | D15: Month 13 | E15: =MIN(E14*(1+$M$3),'Raw_Canada_Baseline'!$B$2) -> 564883.51 | F15: =MIN(F14*(1+$M$4),'Raw_Canada_Baseline'!$B$2) -> 621950.38 | G15: =MIN(G14*(1+$M$5),'Raw_Canada_Baseline'!$B$2) -> 684298.24 | H15: =E15/'Raw_Canada_Baseline'!$B$2 -> 0.062764835 | I15: =F15/'Raw_Canada_Baseline'!$B$2 -> 0.069105598 | J15: =G15/'Raw_Canada_Baseline'!$B$2 -> 0.076033138
A16: ='Raw_UK_API_Data'!A16 -> 45839 | B16: ='Raw_UK_API_Data'!C16 -> 2040365267 | C16: =IFERROR((B16/B15)-1,"") -> 0.034899761 | D16: Month 14 | E16: =MIN(E15*(1+$M$3),'Raw_Canada_Baseline'!$B$2) -> 574850.31 | F16: =MIN(F15*(1+$M$4),'Raw_Canada_Baseline'!$B$2) -> 637627.08 | G16: =MIN(G15*(1+$M$5),'Raw_Canada_Baseline'!$B$2) -> 706720.93 | H16: =E16/'Raw_Canada_Baseline'!$B$2 -> 0.063872257 | I16: =F16/'Raw_Canada_Baseline'!$B$2 -> 0.070847454 | J16: =G16/'Raw_Canada_Baseline'!$B$2 -> 0.078524548
A17: ='Raw_UK_API_Data'!A17 -> 45870 | B17: ='Raw_UK_API_Data'!C17 -> 2070105099 | C17: =IFERROR((B17/B16)-1,"") -> 0.014575739 | D17: Month 15 | E17: =MIN(E16*(1+$M$3),'Raw_Canada_Baseline'!$B$2) -> 584992.97 | F17: =MIN(F16*(1+$M$4),'Raw_Canada_Baseline'!$B$2) -> 653698.93 | G17: =MIN(G16*(1+$M$5),'Raw_Canada_Baseline'!$B$2) -> 729878.36 | H17: =E17/'Raw_Canada_Baseline'!$B$2 -> 0.064999219 | I17: =F17/'Raw_Canada_Baseline'!$B$2 -> 0.072633214 | J17: =G17/'Raw_Canada_Baseline'!$B$2 -> 0.081097595
... A26: ='Raw_UK_API_Data'!A26 -> 46143 | B26: ='Raw_UK_API_Data'!C26 -> 2685988494 | C26: =IFERROR((B26/B25)-1,"") -> 0.069695425 | D26: Month 24 | E26: =MIN(E25*(1+$M$3),'Raw_Canada_Baseline'!$B$2) -> 684720.82 | F26: =MIN(F25*(1+$M$4),'Raw_Canada_Baseline'!$B$2) -> 817856.16 | G26: =MIN(G25*(1+$M$5),'Raw_Canada_Baseline'!$B$2) -> 975603.32 | H26: =E26/'Raw_Canada_Baseline'!$B$2 -> 0.076080091 | I26: =F26/'Raw_Canada_Baseline'!$B$2 -> 0.090872906 | J26: =G26/'Raw_Canada_Baseline'!$B$2 -> 0.10840037

Sheet ME&A forecast
A1: Metric Name | B1: Value / Detail
A2: 2025 Baseline Global API Volume | B2: 1.37E+11
A3: 2029 Projected Global API Volume | B3: 7.20E+11
A4: Ecosystem Volume Growth Rate | B4: 427%
A5: Primary Tech Driver | B5: Generative AI (GenAI) & Personalization
A6: Target Emerging High-Growth Market | B6: Middle East & Africa

Sheet Launch_Dates
A1: Country | B1: Launch Date | C1: Notes
A2: UK | B2: 43113 | C2: Open Banking launch date
A3: Australia | B3: 44013 | C3: Consumer Data Right banking launch
A4: US | B4: 43831 | C4: Proxy — no single launch; FDX adoption baseline
A5: Canada | B5: 46023 | C5: Phase 1 target, from Raw_Canada_Baseline

Sheet Raw_India_AA
A1: Column2 | B1: Column3
A3: Metric | B3: Value
A4: :--- | B4: :---
A5: **Consent Requests** | B5: 24+ crore
A6: **Linked Accounts** | B6: 18+ crore
A7: **Total Loan Value Disbursed** | B7: ₹1.6 lakh crore
A8: **Total Loan Accounts** | B8: 1.8+ crore

Sheet Raw_US_Adoption
A1: Column1 | B1: Column2 | C1: Column3 | D1: Months Since Launch
A2: Open Banking Adoption in the United States | D2: =IFERROR(DATEDIF(Launch_Dates!$B$4,IF(ISNUMBER(C2),DATE(C2,1,1),IF(LEN(TRIM(C2))=4,DATE(VALUE(TRIM(C2)),1,1),DATEVALUE("1 "&C2))),"m"),"")
D3: =IFERROR(DATEDIF(Launch_Dates!$B$4,IF(ISNUMBER(C3),DATE(C3,1,1),IF(LEN(TRIM(C3))=4,DATE(VALUE(TRIM(C3)),1,1),DATEVALUE("1 "&C3))),"m"),"")
A4: US Open Banking Metric | B4: Value | C4: Period | D4: =IFERROR(DATEDIF(Launch_Dates!$B$4,IF(ISNUMBER(C4),DATE(C4,1,1),IF(LEN(TRIM(C4))=4,DATE(VALUE(TRIM(C4)),1,1),DATEVALUE("1 "&C4))),"m"),"")
A5: Bank Adoption Rate | B5: 52% | C5: 2025 | D5: =IFERROR(DATEDIF(Launch_Dates!$B$4,IF(ISNUMBER(C5),DATE(C5,1,1),IF(LEN(TRIM(C5))=4,DATE(VALUE(TRIM(C5)),1,1),DATEVALUE("1 "&C5))),"m"),"") -> 60
A6: FDX Customer API Connections | B6: 114 million | C6: April 2025 | D6: =IFERROR(DATEDIF(Launch_Dates!$B$4,IF(ISNUMBER(C6),DATE(C6,1,1),IF(LEN(TRIM(C6))=4,DATE(VALUE(TRIM(C6)),1,1),DATEVALUE("1 "&C6))),"m"),"") -> 63
A7: FDX Connections (prior year) | B7: 76 million | C7: April 2024 | D7: =IFERROR(DATEDIF(Launch_Dates!$B$4,IF(ISNUMBER(C7),DATE(C7,1,1),IF(LEN(TRIM(C7))=4,DATE(VALUE(TRIM(C7)),1,1),DATEVALUE("1 "&C7))),"m"),"") -> 51
A8: FDX Data Providers | B8: 1,000+ | C8: 2025 | D8: =IFERROR(DATEDIF(Launch_Dates!$B$4,IF(ISNUMBER(C8),DATE(C8,1,1),IF(LEN(TRIM(C8))=4,DATE(VALUE(TRIM(C8)),1,1),DATEVALUE("1 "&C8))),"m"),"") -> 60
A9: FDX Member Organizations | B9: 200+ | C9: 2025 | D9: =IFERROR(DATEDIF(Launch_Dates!$B$4,IF(ISNUMBER(C9),DATE(C9,1,1),IF(LEN(TRIM(C9))=4,DATE(VALUE(TRIM(C9)),1,1),DATEVALUE("1 "&C9))),"m"),"") -> 60
A10: Screen Scraping Share (est.) | B10: 20% | C10: 2025 | D10: =IFERROR(DATEDIF(Launch_Dates!$B$4,IF(ISNUMBER(C10),DATE(C10,1,1),IF(LEN(TRIM(C10))=4,DATE(VALUE(TRIM(C10)),1,1),DATEVALUE("1 "&C10))),"m"),"") -> 60
D11: =IFERROR(DATEDIF(Launch_Dates!$B$4,IF(ISNUMBER(C11),DATE(C11,1,1),IF(LEN(TRIM(C11))=4,DATE(VALUE(TRIM(C11)),1,1),DATEVALUE("1 "&C11))),"m"),"")
A12: Source: FDX, Statista, CFPB | D12: =IFERROR(DATEDIF(Launch_Dates!$B$4,IF(ISNUMBER(C12),DATE(C12,1,1),IF(LEN(TRIM(C12))=4,DATE(VALUE(TRIM(C12)),1,1),DATEVALUE("1 "&C12))),"m"),"")

Sheet Regulation by Country
A1: Column1 | B1: Column2 | C1: Column3 | D1: Column4
A2: Open Banking Regulation by Country
A4: Country / Region | B4: Framework | C4: Status (April 2026) | D4: Mandate Type
A5: European Union | B5: PSD2 / PSD3 | C5: Enforced since 2018 | D5: Mandatory
A6: United Kingdom | B6: Open Banking Standard | C6: Active, 95% compliance | D6: Mandatory
A7: United States | B7: CFPB Section 1033 | C7: Paused (litigation) | D7: Pending
A8: Canada | B8: Consumer-Driven Banking | C8: Framework in development | D8: Planned
A9: Australia | B9: Consumer Data Right | C9: Enforced since 2020 | D9: Mandatory
A10: Brazil | B10: Open Finance | C10: Enforced since 2021 | D10: Mandatory
A11: India | B11: Account Aggregator | C11: Active since 2021 | D11: Licensing-based
A12: Saudi Arabia | B12: Open Banking Policy | C12: Enforced since 2023 | D12: Mandatory
A14: Source: European Commission, CFPB, Reserve Bank of India, Central Bank of Brazil

Sheet Raw_AU_Availability
A1: % Availability (AVG) | B1: Month Year MMM-YYYY | C1: Months Since Launch
A2: 0.9726 | B2: 45658 | C2: =IFERROR(DATEDIF(Launch_Dates!$B$3,B2,"m"),"") -> 54
A3: 0.9727 | B3: 45689 | C3: =IFERROR(DATEDIF(Launch_Dates!$B$3,B3,"m"),"") -> 55
A4: 0.9715 | B4: 45717 | C4: =IFERROR(DATEDIF(Launch_Dates!$B$3,B4,"m"),"") -> 56
A5: 0.9651 | B5: 45748 | C5: =IFERROR(DATEDIF(Launch_Dates!$B$3,B5,"m"),"") -> 57
A6: 0.9648 | B6: 45778 | C6: =IFERROR(DATEDIF(Launch_Dates!$B$3,B6,"m"),"") -> 58
A7: 0.965 | B7: 45809 | C7: =IFERROR(DATEDIF(Launch_Dates!$B$3,B7,"m"),"") -> 59
A8: 0.9703 | B8: 45839 | C8: =IFERROR(DATEDIF(Launch_Dates!$B$3,B8,"m"),"") -> 60
A9: 0.976 | B9: 45870 | C9: =IFERROR(DATEDIF(Launch_Dates!$B$3,B9,"m"),"") -> 61
A10: 0.9802 | B10: 45901 | C10: =IFERROR(DATEDIF(Launch_Dates!$B$3,B10,"m"),"") -> 62
A11: 0.9876 | B11: 45931 | C11: =IFERROR(DATEDIF(Launch_Dates!$B$3,B11,"m"),"") -> 63
A12: 0.9885 | B12: 45962 | C12: =IFERROR(DATEDIF(Launch_Dates!$B$3,B12,"m"),"") -> 64
A13: 0.9523 | B13: 45992 | C13: =IFERROR(DATEDIF(Launch_Dates!$B$3,B13,"m"),"") -> 65
... A20: 0.9874 | B20: 46204 | C20: =IFERROR(DATEDIF(Launch_Dates!$B$3,B20,"m"),"") -> 72

Sheet Raw_AU_API_Invocations
A1: Date | B1: Months Since Launch | C1: API Invocations
A2: 45658 | B2: =IFERROR(DATEDIF(Launch_Dates!$B$3,A2,"m"),"") -> 54 | C2: 5806118
A3: 45659 | B3: =IFERROR(DATEDIF(Launch_Dates!$B$3,A3,"m"),"") -> 54 | C3: 5905738
A4: 45660 | B4: =IFERROR(DATEDIF(Launch_Dates!$B$3,A4,"m"),"") -> 54 | C4: 5894974
A5: 45661 | B5: =IFERROR(DATEDIF(Launch_Dates!$B$3,A5,"m"),"") -> 54 | C5: 5721069
A6: 45662 | B6: =IFERROR(DATEDIF(Launch_Dates!$B$3,A6,"m"),"") -> 54 | C6: 5968843
A7: 45663 | B7: =IFERROR(DATEDIF(Launch_Dates!$B$3,A7,"m"),"") -> 54 | C7: 6036058
A8: 45664 | B8: =IFERROR(DATEDIF(Launch_Dates!$B$3,A8,"m"),"") -> 54 | C8: 6043566
A9: 45665 | B9: =IFERROR(DATEDIF(Launch_Dates!$B$3,A9,"m"),"") -> 54 | C9: 6085984
A10: 45666 | B10: =IFERROR(DATEDIF(Launch_Dates!$B$3,A10,"m"),"") -> 54 | C10: 6122979
A11: 45667 | B11: =IFERROR(DATEDIF(Launch_Dates!$B$3,A11,"m"),"") -> 54 | C11: 6118739
A12: 45668 | B12: =IFERROR(DATEDIF(Launch_Dates!$B$3,A12,"m"),"") -> 54 | C12: 5871858
A13: 45669 | B13: =IFERROR(DATEDIF(Launch_Dates!$B$3,A13,"m"),"") -> 54 | C13: 6081275
... A560: 46216 | B560: =IFERROR(DATEDIF(Launch_Dates!$B$3,A560,"m"),"") -> 72 | C560: 12806643

Sheet Raw_AU_Authorisations
A1: Date | B1: Months Since Launch | C1: Active Ongoing Authorisations
A2: 45658 | B2: =IFERROR(DATEDIF(Launch_Dates!$B$3,A2,"m"),"") -> 54 | C2: 371408
A3: 45659 | B3: =IFERROR(DATEDIF(Launch_Dates!$B$3,A3,"m"),"") -> 54 | C3: 372943
A4: 45660 | B4: =IFERROR(DATEDIF(Launch_Dates!$B$3,A4,"m"),"") -> 54 | C4: 374721
A5: 45661 | B5: =IFERROR(DATEDIF(Launch_Dates!$B$3,A5,"m"),"") -> 54 | C5: 377052
A6: 45662 | B6: =IFERROR(DATEDIF(Launch_Dates!$B$3,A6,"m"),"") -> 54 | C6: 378828
A7: 45663 | B7: =IFERROR(DATEDIF(Launch_Dates!$B$3,A7,"m"),"") -> 54 | C7: 379393
A8: 45664 | B8: =IFERROR(DATEDIF(Launch_Dates!$B$3,A8,"m"),"") -> 54 | C8: 383528
A9: 45665 | B9: =IFERROR(DATEDIF(Launch_Dates!$B$3,A9,"m"),"") -> 54 | C9: 385936
A10: 45666 | B10: =IFERROR(DATEDIF(Launch_Dates!$B$3,A10,"m"),"") -> 54 | C10: 387794
A11: 45667 | B11: =IFERROR(DATEDIF(Launch_Dates!$B$3,A11,"m"),"") -> 54 | C11: 389617
A12: 45668 | B12: =IFERROR(DATEDIF(Launch_Dates!$B$3,A12,"m"),"") -> 54 | C12: 389591
A13: 45669 | B13: =IFERROR(DATEDIF(Launch_Dates!$B$3,A13,"m"),"") -> 54 | C13: 391680
... A560: 46216 | B560: =IFERROR(DATEDIF(Launch_Dates!$B$3,A560,"m"),"") -> 72 | C560: 1385016

Sheet Summary_Dashboard_Feed 
A1: Country | B1: Months Since Launch | C1: Metric Name | D1: Metric Value | F1: Bank | G1: Product Line | H1: Revenue at Risk - Base ($M) | K1: Milestone | L1: Target Date | M1: Status | N1: Days Remaining
A2: UK | B2: 75 | C2: API Calls Successful | D2: 1520925954 | F2: RBC | G2: Payments | H2: 341.50038 | K2: Royal Assent | L2: 46107 | M2: Complete | N2: -114
A3: UK | B3: 76 | C3: API Calls Successful | D3: 1494386712 | F3: RBC | G3: Lending | H3: 90.418542 | K3: Phase 1/Read | L3: 46023 | M3: Upcoming | N3: -198
A4: UK | B4: 77 | C4: API Calls Successful | D4: 1564131601 | F4: RBC | G4: Deposits | H4: 168.80551 | K4: Phase 2/Write-Payments | L4: 46569 | M4: Upcoming | N4: 348
A5: UK | B5: 78 | C5: API Calls Successful | D5: 1581848583 | F5: TD | G5: Payments | H5: 375.95939
A6: UK | B6: 79 | C6: API Calls Successful | D6: 1603209493 | F6: TD | G6: Lending | H6: 93.989847
A7: UK | B7: 80 | C7: API Calls Successful | D7: 1747365142 | F7: TD | G7: Deposits | H7: 169.18172
A8: UK | B8: 81 | C8: API Calls Successful | D8: 1747874987 | F8: BMO | G8: Payments | H8: 222.85672 | K8: Bank | L8: Public Commitment Level (1-5) | M8: Digital Exposure Estimate (1-5)
A9: UK | B9: 82 | C9: API Calls Successful | D9: 1853825146 | F9: BMO | G9: Lending | H9: 55.714179 | K9: RBC | L9: 5 | M9: 5
A10: UK | B10: 83 | C10: API Calls Successful | D10: 1909058414 | F10: BMO | G10: Deposits | H10: 100.28552 | K10: TD | L10: 5 | M10: 5
A11: UK | B11: 84 | C11: API Calls Successful | D11: 1780842248 | F11: CIBC | G11: Payments | H11: 218.09498 | K11: BMO | L11: 5 | M11: 4
A12: UK | B12: 85 | C12: API Calls Successful | D12: 1990052545 | F12: CIBC | G12: Lending | H12: 54.523744 | K12: CIBC | L12: 2 | M12: 3
A13: UK | B13: 86 | C13: API Calls Successful | D13: 1952040978 | F13: CIBC | G13: Deposits | H13: 98.142739 | K13: Scotiabank (BNS) | L13: 3 | M13: 3
A14: UK | B14: 87 | C14: API Calls Successful | D14: 1998627582 | F14: Scotiabank (BNS) | G14: Payments | H14: 243.99375 | K14: National Bank | L14: 3 | M14: 2
A15: UK | B15: 88 | C15: API Calls Successful | D15: 1971558351 | F15: Scotiabank (BNS) | G15: Lending | H15: 60.998438
A16: UK | B16: 89 | C16: API Calls Successful | D16: 2040365267 | F16: Scotiabank (BNS) | G16: Deposits | H16: 109.79719
A17: UK | B17: 90 | C17: API Calls Successful | D17: 2070105099 | F17: National Bank | G17: Payments | H17: 45.399195 | K17: KPI | L17: Value | M17: Unit | N17: Source
A18: UK | B18: 91 | C18: API Calls Successful | D18: 2019432214 | F18: National Bank | G18: Lending | H18: 25.221775 | K18: At-risk population | L18: ='Raw_Canada_Baseline'!B2 -> 9000000 | M18: people | N18: Raw_Canada_Baseline
A19: UK | B19: 92 | C19: API Calls Successful | D19: 2168402057 | F19: National Bank | G19: Deposits | H19: 62.045567 | K19: Days to Phase 1 | L19: =_xlfn.XLOOKUP("Phase 1/Read",Calc_Chart3_Milestones!A:A,Calc_Chart3_Milestones!D:D) -> -198 | M19: days | N19: Calc_Chart3_Milestones
A20: UK | B20: 93 | C20: API Calls Successful | D20: 2211669970 | K20: Total estimated revenue-at-risk | L20: =SUM(Calc_Chart2_RevenueProductLine!C:C) -> 2536.9292 | M20: $M | N20: Calc_Chart2_RevenueProductLine
A21: UK | B21: 94 | C21: API Calls Successful | D21: 2344465731
A22: UK | B22: 95 | C22: API Calls Successful | D22: 2404347087
A23: UK | B23: 96 | C23: API Calls Successful | D23: 2233344488
A24: UK | B24: 97 | C24: API Calls Successful | D24: 2539426430
A25: UK | B25: 98 | C25: API Calls Successful | D25: 2510984372
A26: UK | B26: 99 | C26: API Calls Successful | D26: 2685988494
A27: Australia | B27: 54 | C27: Avg Active Ongoing Authorisations | D27: 378614.81
A28: Australia | B28: 55 | C28: Avg Active Ongoing Authorisations | D28: 412739.96
A29: Australia | B29: 56 | C29: Avg Active Ongoing Authorisations | D29: 452307.03
A30: Australia | B30: 57 | C30: Avg Active Ongoing Authorisations | D30: 451724.5
A31: Australia | B31: 58 | C31: Avg Active Ongoing Authorisations | D31: 511812.84
A32: Australia | B32: 59 | C32: Avg Active Ongoing Authorisations | D32: 550456.3
... A140: Canada | B140: 24 | C140: Optimistic | D140: 0.10840037

Sheet Calc_Revenue_At_Risk
A1: Bank | B1: Segment Revenue FY25 ($M) | C1: Exposed Revenue Share (%) | D1: Exposed Revenue Base ($M) | E1: Adoption % — Conservative | F1: Adoption % — Base | G1: Adoption % — Optimistic | H1: Revenue at Risk — Conservative ($M) | I1: Revenue at Risk — Base ($M) | J1: Revenue at Risk — Optimistic ($M) | K1: Base Case Risk as % of Segment Revenue | L1: Rank (Most Exposed = 1)
A2: =PC_Segment!A2 -> RBC | B2: =PC_Segment!E2 -> 19900 | C2: =(2425+1333)/19900 -> 0.18884422 | D2: =B2*C2 -> 3758 | E2: =Calc_Adoption_Forecast!$H$26 -> 0.076080091 | F2: =Calc_Adoption_Forecast!$I$26 -> 0.090872906 | G2: =Calc_Adoption_Forecast!$J$26 -> 0.10840037 | H2: =D2*E2 -> 285.90898 | I2: =D2*F2 -> 341.50038 | J2: =D2*G2 -> 407.36859 | K2: =I2/B2 -> 0.017160823 | L2: =RANK(I2,$I$2:$I$7,0) -> 1
A3: =PC_Segment!A3 -> TD | B3: =PC_Segment!E3 -> 20686 | C3: 0.14 | D3: =B3*C3 -> 2896.04 | E3: =Calc_Adoption_Forecast!$H$26 -> 0.076080091 | F3: =Calc_Adoption_Forecast!$I$26 -> 0.090872906 | G3: =Calc_Adoption_Forecast!$J$26 -> 0.10840037 | H3: =D3*E3 -> 220.33099 | I3: =D3*F3 -> 263.17157 | J3: =D3*G3 -> 313.9318 | K3: =I3/B3 -> 0.012722207 | L3: =RANK(I3,$I$2:$I$7,0) -> 2
A4: =PC_Segment!A4 -> BMO | B4: =PC_Segment!E4 -> 12262 | C4: 0.14 | D4: =B4*C4 -> 1716.68 | E4: =Calc_Adoption_Forecast!$H$26 -> 0.076080091 | F4: =Calc_Adoption_Forecast!$I$26 -> 0.090872906 | G4: =Calc_Adoption_Forecast!$J$26 -> 0.10840037 | H4: =D4*E4 -> 130.60517 | I4: =D4*F4 -> 155.9997 | J4: =D4*G4 -> 186.08875 | K4: =I4/B4 -> 0.012722207 | L4: =RANK(I4,$I$2:$I$7,0) -> 4
A5: =PC_Segment!A5 -> CIBC | B5: =PC_Segment!E5 -> 12000 | C5: 0.14 | D5: =B5*C5 -> 1680 | E5: =Calc_Adoption_Forecast!$H$26 -> 0.076080091 | F5: =Calc_Adoption_Forecast!$I$26 -> 0.090872906 | G5: =Calc_Adoption_Forecast!$J$26 -> 0.10840037 | H5: =D5*E5 -> 127.81455 | I5: =D5*F5 -> 152.66648 | J5: =D5*G5 -> 182.11262 | K5: =I5/B5 -> 0.012722207 | L5: =RANK(I5,$I$2:$I$7,0) -> 5
A6: =PC_Segment!A6 -> Scotiabank (BNS) | B6: =PC_Segment!E6 -> 13425 | C6: 0.14 | D6: =B6*C6 -> 1879.5 | E6: =Calc_Adoption_Forecast!$H$26 -> 0.076080091 | F6: =Calc_Adoption_Forecast!$I$26 -> 0.090872906 | G6: =Calc_Adoption_Forecast!$J$26 -> 0.10840037 | H6: =D6*E6 -> 142.99253 | I6: =D6*F6 -> 170.79563 | J6: =D6*G6 -> 203.73849 | K6: =I6/B6 -> 0.012722207 | L6: =RANK(I6,$I$2:$I$7,0) -> 3
A7: =PC_Segment!A7 -> National Bank | B7: =PC_Segment!E7 -> 5551 | C7: 0.09 | D7: =B7*C7 -> 499.59 | E7: =Calc_Adoption_Forecast!$H$26 -> 0.076080091 | F7: =Calc_Adoption_Forecast!$I$26 -> 0.090872906 | G7: =Calc_Adoption_Forecast!$J$26 -> 0.10840037 | H7: =D7*E7 -> 38.008852 | I7: =D7*F7 -> 45.399195 | J7: =D7*G7 -> 54.15574 | K7: =I7/B7 -> 0.0081785616 | L7: =RANK(I7,$I$2:$I$7,0) -> 6
G8: Big Six aggregate revenue-at-risk | H8: =SUM(Table17[Revenue at Risk — Conservative ($M)]) -> 945.66107 | I8: =SUM(Table17[Revenue at Risk — Base ($M)]) -> 1129.533 | J8: =SUM(Table17[Revenue at Risk — Optimistic ($M)]) -> 1347.396

Sheet Regulatory Timeline
A1: Year | B1: Milestone | C1: Detail | D1: Source
A2: 2015 | B2: PSD2 adopted | C2: Second Payment Services Directive adopted by the EU | D2: Konsentus
A3: 2018 | B3: PSD2 in force | C3: PSD2 implemented across member states; XS2A (access-to-account) clause requires banks to grant licensed TPPs access to account data/payments with customer consent | D3: Konsentus
A4: 2018 | B4: EBA technical standards | C4: EBA creates Strong Customer Authentication (SCA) and secure API technical standards to operationalize PSD2 | D4: Konsentus
A5: 2026 | B5: PSD3 finalization | C5: EU reported to be finalizing PSD3 (successor directive, alongside PSR - Payment Services Regulation) | D5: Spark / Kontomatik

Sheet PSD2-PSD3 Data Log
A1: Metric | B1: Value | C1: Unit | D1: Geography | E1: As-Of Date | F1: Date Retrieved | G1: Source Name | H1: URL | I1: Status | J1: Notes
A2: Licensed EU banks PSD2-compliant | B2: 94% | C2: % | D2: EU-wide | E2: 2025 | F2: 46221 | G2: CoinLaw / SQ Magazine | H2: https://coinlaw.io/open-banking-adoption-statistics/ | I2: Needs Verification | J2: Widely repeated figure across secondary sources; no single primary source found. Treat as a citable industry consensus stat, not an official EBA figure.
A3: Europe's share of global open banking revenue | B3: 36.4% | C3: % | D3: EU-wide | E3: 2024 | F3: 46221 | G3: SQ Magazine | H3: https://sqmagazine.co.uk/open-banking-adoption-statistics/ | I3: Needs Verification | J3: Secondary aggregator source
A4: PSD2 adoption (legislative) | B4: 2015 | C4: year | D4: EU-wide | E4: 2015 | F4: 46221 | G4: Konsentus | H4: https://www.konsentus.com/the-unfinished-story-of-european-open-banking/ | I4: Pulled | J4: Directive adopted by the EU
A5: PSD2 implementation (in force) | B5: 2018 | C5: year | D5: EU-wide | E5: 2018 | F5: 46221 | G5: Konsentus | H5: https://www.konsentus.com/the-unfinished-story-of-european-open-banking/ | I5: Pulled | J5: XS2A (access-to-account) clause is the key open banking provision
A6: PSD3 status | B6: Finalizing | C6: status | D6: EU-wide | E6: 2026 | F6: 46221 | G6: Spark | H6: https://www.spark.money/research/open-banking-global-state | I6: Needs Verification | J6: EU reported to be finalizing PSD3 in 2026 - confirm exact stage (trilogue/vote) before citing as fact
A7: No single EU reporting body | B7: N/A - qualitative | C7: flag | D7: EU-wide | E7: 2026 | F7: 46221 | G7: Konsentus | H7: https://www.konsentus.com/the-unfinished-story-of-european-open-banking/ | I7: Pulled | J7: Key caveat: cite this explicitly when presenting EU stats to explain absence of a clean adoption curve
A8: EBA Register of Payment Institutions | B8: Live register (count not yet pulled) | C8: count | D8: EU-wide | E8: current | F8: 46221 | G8: EBA | H8: https://www.eba.europa.eu/registers/payment-institutions-register | I8: Not Started | J8: Closest thing to an official EBA number - closest proxy for licensed TPP count; check for CSV export on page
A9: UK active open banking users (external benchmark) | B9: 13.3 | C9: million | D9: UK | E9: 2025-03 | F9: 46221 | G9: Noda (citing Yapily/OBL) | H9: https://noda.live/articles/open-banking-in-europe | I9: Needs Verification | J9: Used as external comparator, not an EU figure; cross-check against your Phase 2 UK CSV data

Sheet Raw_UK_API_Data
A1: Metric | B1: Months Since Launch | C1: # of API Calls Successful | D1: # of API Calls Successful - AIS | E1: # of API Calls Successful - PIS | F1: # of API Calls Successful - COF | G1: # of Non VRP Domestic Payments Successful | H1: Vol VRP Payment Succeeded | I1: # of API Calls Failed | J1: # of API Calls failed for Business Reasons | K1: % of API Calls failed for Business Reasons | L1: # of API Calls failed for Technical Reasons | M1: % of API Calls failed for Technical Reasons | N1: # of API Calls with Rejected Status | O1: % of API Calls with Rejected Status | P1: API Response Time | Q1: Availability % | R1: Availability % - AIS | S1: Availability % - PIS | T1: Availability % - Weighted | U1: Availability % - Weighted - AIS | V1: Availability % - Weighted - PIS
A2: 45413 | B2: =IFERROR(DATEDIF(Launch_Dates!$B$2,A2,"m"),"") -> 75 | C2: 1520925954 | D2: 1264447046 | E2: 82456927 | F2: 2325324 | G2: 15605632 | H2: 1773660 | I2: 15171558 | J2: 5562462 | K2: 0.0036 | L2: 9609096 | M2: 0.0063 | N2: 1826366 | O2: 0.0012 | P2: 375 | Q2: 0.9945 | R2: 0.9862 | S2: 0.9949 | T2: 0.9954 | U2: 0.9954 | V2: 0.996
A3: 45444 | B3: =IFERROR(DATEDIF(Launch_Dates!$B$2,A3,"m"),"") -> 76 | C3: 1494386712 | D3: 1241523086 | E3: 78599356 | F3: 2457001 | G3: 15911890 | H3: 1977979 | I3: 7023040 | J3: 5343262 | K3: 0.0036 | L3: 1679778 | M3: 0.0011 | N3: 2003609 | O3: 0.0013 | P3: 367 | Q3: 0.9961 | R3: 0.9677 | S3: 0.9987 | T3: 0.9983 | U3: 0.9982 | V3: 0.999
A4: 45474 | B4: =IFERROR(DATEDIF(Launch_Dates!$B$2,A4,"m"),"") -> 77 | C4: 1564131601 | D4: 1297145620 | E4: 82889379 | F4: 2801520 | G4: 17083773 | H4: 2450491 | I4: 6281328 | J4: 5156883 | K4: 0.0033 | L4: 1124445 | M4: 0.0007 | N4: 2264151 | O4: 0.0014 | P4: 360 | Q4: 0.9979 | R4: 0.9907 | S4: 0.9985 | T4: 0.9993 | U4: 0.9993 | V4: 0.9992
A5: 45505 | B5: =IFERROR(DATEDIF(Launch_Dates!$B$2,A5,"m"),"") -> 78 | C5: 1581848583 | D5: 1314276464 | E5: 87127444 | F5: 2828592 | G5: 17314847 | H5: 2723643 | I5: 6609954 | J5: 5404610 | K5: 0.0034 | L5: 1205344 | M5: 0.0008 | N5: 1961826 | O5: 0.0012 | P5: 339 | Q5: 0.999 | R5: 0.994 | S5: 0.9995 | T5: 0.9994 | U5: 0.9994 | V5: 0.9996
A6: 45536 | B6: =IFERROR(DATEDIF(Launch_Dates!$B$2,A6,"m"),"") -> 79 | C6: 1603209493 | D6: 1327489079 | E6: 84110872 | F6: 2812465 | G6: 17228045 | H6: 2747092 | I6: 9990689 | J6: 6605822 | K6: 0.0041 | L6: 3384867 | M6: 0.0021 | N6: 2086105 | O6: 0.0013 | P6: 351 | Q6: 0.9944 | R6: 0.9901 | S6: 0.9947 | T6: 0.9964 | U6: 0.9953 | V6: 0.9956
A7: 45566 | B7: =IFERROR(DATEDIF(Launch_Dates!$B$2,A7,"m"),"") -> 80 | C7: 1747365142 | D7: 1441900835 | E7: 91508305 | F7: 2922481 | G7: 18660501 | H7: 3020455 | I7: 8025519 | J7: 5279507 | K7: 0.003 | L7: 2746012 | M7: 0.0016 | N7: 2148507 | O7: 0.0012 | P7: 350 | Q7: 0.9964 | R7: 0.9975 | S7: 0.9964 | T7: 0.9983 | U7: 0.9972 | V7: 0.9967
A8: 45597 | B8: =IFERROR(DATEDIF(Launch_Dates!$B$2,A8,"m"),"") -> 81 | C8: 1747874987 | D8: 1435960853 | E8: 94351970 | F8: 2958455 | G8: 19006914 | H8: 3117690 | I8: 7348517 | J8: 5376888 | K8: 0.0031 | L8: 1971629 | M8: 0.0011 | N8: 2153426 | O8: 0.0012 | P8: 361 | Q8: 0.9961 | R8: 0.9936 | S8: 0.9964 | T8: 0.9981 | U8: 0.9969 | V8: 0.9965
A9: 45627 | B9: =IFERROR(DATEDIF(Launch_Dates!$B$2,A9,"m"),"") -> 82 | C9: 1853825146 | D9: 1481683277 | E9: 99853289 | F9: 3236202 | G9: 20366495 | H9: 3296403 | I9: 14782129 | J9: 6090342 | K9: 0.0033 | L9: 8691787 | M9: 0.0047 | N9: 2353272 | O9: 0.0013 | P9: 328 | Q9: 0.9975 | R9: 0.9981 | S9: 0.9975 | T9: 0.9979 | U9: 0.9975 | V9: 0.9977
A10: 45658 | B10: =IFERROR(DATEDIF(Launch_Dates!$B$2,A10,"m"),"") -> 83 | C10: 1909058414 | D10: 1533540636 | E10: 109535541 | F10: 4207622 | G10: 22015521 | H10: 3293918 | I10: 7996778 | J10: 6076198 | K10: 0.0032 | L10: 1920580 | M10: 0.001 | N10: 2768553 | O10: 0.0014 | P10: 331 | Q10: 0.9952 | R10: 0.9919 | S10: 0.9959 | T10: 0.998 | U10: 0.998 | V10: 0.9973
A11: 45689 | B11: =IFERROR(DATEDIF(Launch_Dates!$B$2,A11,"m"),"") -> 84 | C11: 1780842248 | D11: 1452734336 | E11: 95703994 | F11: 3376042 | G11: 20311952 | H11: 3291832 | I11: 8171786 | J11: 6005449 | K11: 0.0034 | L11: 2166337 | M11: 0.0012 | N11: 2261641 | O11: 0.0013 | P11: 337 | Q11: 0.9989 | R11: 0.9948 | S11: 0.9994 | T11: 0.9995 | U11: 0.9986 | V11: 0.9989
A12: 45717 | B12: =IFERROR(DATEDIF(Launch_Dates!$B$2,A12,"m"),"") -> 85 | C12: 1990052545 | D12: 1614205269 | E12: 112394467 | F12: 4155121 | G12: 23540588 | H12: 3671764 | I12: 12658659 | J12: 8067056 | K12: 0.004 | L12: 4591603 | M12: 0.0023 | N12: 2667247 | O12: 0.0013 | P12: 351 | Q12: 0.9948 | R12: 0.9889 | S12: 0.9956 | T12: 0.9955 | U12: 0.9953 | V12: 0.9957
A13: 45748 | B13: =IFERROR(DATEDIF(Launch_Dates!$B$2,A13,"m"),"") -> 86 | C13: 1952040978 | D13: 1586161225 | E13: 109819546 | F13: 4272163 | G13: 23445538 | H13: 3660316 | I13: 9149096 | J13: 6854063 | K13: 0.0035 | L13: 2295033 | M13: 0.0012 | N13: 2754726 | O13: 0.0014 | P13: 350 | Q13: 0.9972 | R13: 0.9955 | S13: 0.998 | T13: 0.998 | U13: 0.9977 | V13: 0.9984
... A26: 46143 | B26: =IFERROR(DATEDIF(Launch_Dates!$B$2,A26,"m"),"") -> 99 | C26: 2685988494 | D26: 2107382290 | E26: 165071662 | F26: 5518659 | G26: 32816197 | H26: 7247222 | I26: 10606218 | J26: 9491669 | K26: 0.0035 | L26: 1114549 | M26: 0.0004 | N26: 4074443 | O26: 0.0015 | P26: 399.04921 | Q26: 0.9954 | R26: 0.9955 | S26: 0.9955 | T26: 0.9998 | U26: 0.9998 | V26: 0.9997

Sheet AU_Pivots
A1: AU Authorisations — Average by Months Since Launch | E1: AU API Invocations — Sum by Months Since Launch
A3: Row Labels | B3: Average of Active Ongoing Authorisations | E3: Row Labels | F3: Sum of API Invocations
A4: 54 | B4: 378614.81 | E4: 54 | F4: 203964060
A5: 55 | B5: 412739.96 | E5: 55 | F5: 156487437
A6: 56 | B6: 452307.03 | E6: 56 | F6: 186668328
A7: 57 | B7: 451724.5 | E7: 57 | F7: 201917631
A8: 58 | B8: 511812.84 | E8: 58 | F8: 223914900
A9: 59 | B9: 550456.3 | E9: 59 | F9: 217410079
A10: 60 | B10: 580366.65 | E10: 60 | F10: 236797876
A11: 61 | B11: 628288.84 | E11: 61 | F11: 240330105
A12: 62 | B12: 670071.83 | E12: 62 | F12: 239886536
A13: 63 | B13: 702357.52 | E13: 63 | F13: 308205928
A14: 64 | B14: 791741.93 | E14: 64 | F14: 423922786
A15: 65 | B15: 849936.87 | E15: 65 | F15: 374124536
... A22: 72 | B22: 1351386.8 | E22: 72 | F22: 243049477
A23: Grand Total | B23: 762498.45 | E23: Grand Total | F23: 5913225496

Sheet Calc_Chart1_AdoptionCurve
A1: Country | B1: Months Since Launch | C1: Metric Name | D1: Metric Value
A2: UK | B2: 75 | C2: API Calls Successful | D2: 1520925954
A3: UK | B3: 76 | C3: API Calls Successful | D3: 1494386712
A4: UK | B4: 77 | C4: API Calls Successful | D4: 1564131601
A5: UK | B5: 78 | C5: API Calls Successful | D5: 1581848583
A6: UK | B6: 79 | C6: API Calls Successful | D6: 1603209493
A7: UK | B7: 80 | C7: API Calls Successful | D7: 1747365142
A8: UK | B8: 81 | C8: API Calls Successful | D8: 1747874987
A9: UK | B9: 82 | C9: API Calls Successful | D9: 1853825146
A10: UK | B10: 83 | C10: API Calls Successful | D10: 1909058414
A11: UK | B11: 84 | C11: API Calls Successful | D11: 1780842248
A12: UK | B12: 85 | C12: API Calls Successful | D12: 1990052545
A13: UK | B13: 86 | C13: API Calls Successful | D13: 1952040978
... A140: Canada | B140: 24 | C140: Optimistic | D140: 0.10840037

Sheet Calc_Chart2_RevenueProductLine
A1: Bank | B1: Product Line | C1: Revenue at Risk - Base ($M) | E1: Bank | F1: Segment Revenue FY25 ($M) | G1: Base Adoption % | H1: Payments Share | I1: Lending Share | J1: Deposits Share | K1: Payments Factor | L1: Lending Factor | M1: Deposits Factor | N1: Payments Risk | O1: Lending Risk | P1: Deposits Risk
A2: RBC | B2: Payments | C2: 341.50038 | E2: RBC | F2: 19900 | G2: 0.090872906 | H2: 0.18884422 | I2: 0.5 | J2: 0.31115578 | K2: 1 | L2: 0.1 | M2: 0.3 | N2: 341.50038 | O2: 90.418542 | P2: 168.80551
A3: RBC | B3: Lending | C3: 90.418542 | E3: TD | F3: 20686 | G3: 0.090872906 | H3: 0.2 | I3: 0.5 | J3: 0.3 | K3: 1 | L3: 0.1 | M3: 0.3 | N3: 375.95939 | O3: 93.989847 | P3: 169.18172
A4: RBC | B4: Deposits | C4: 168.80551 | E4: BMO | F4: 12262 | G4: 0.090872906 | H4: 0.2 | I4: 0.5 | J4: 0.3 | K4: 1 | L4: 0.1 | M4: 0.3 | N4: 222.85672 | O4: 55.714179 | P4: 100.28552
A5: TD | B5: Payments | C5: 375.95939 | E5: CIBC | F5: 12000 | G5: 0.090872906 | H5: 0.2 | I5: 0.5 | J5: 0.3 | K5: 1 | L5: 0.1 | M5: 0.3 | N5: 218.09498 | O5: 54.523744 | P5: 98.142739
A6: TD | B6: Lending | C6: 93.989847 | E6: Scotiabank (BNS) | F6: 13425 | G6: 0.090872906 | H6: 0.2 | I6: 0.5 | J6: 0.3 | K6: 1 | L6: 0.1 | M6: 0.3 | N6: 243.99375 | O6: 60.998438 | P6: 109.79719
A7: TD | B7: Deposits | C7: 169.18172 | E7: National Bank | F7: 5551 | G7: 0.090872906 | H7: 0.09 | I7: 0.5 | J7: 0.41 | K7: 1 | L7: 0.1 | M7: 0.3 | N7: 45.399195 | O7: 25.221775 | P7: 62.045567
A8: BMO | B8: Payments | C8: 222.85672
A9: BMO | B9: Lending | C9: 55.714179
A10: BMO | B10: Deposits | C10: 100.28552
A11: CIBC | B11: Payments | C11: 218.09498
A12: CIBC | B12: Lending | C12: 54.523744
A13: CIBC | B13: Deposits | C13: 98.142739
A14: Scotiabank (BNS) | B14: Payments | C14: 243.99375
A15: Scotiabank (BNS) | B15: Lending | C15: 60.998438
A16: Scotiabank (BNS) | B16: Deposits | C16: 109.79719
A17: National Bank | B17: Payments | C17: 45.399195
A18: National Bank | B18: Lending | C18: 25.221775
A19: National Bank | B19: Deposits | C19: 62.045567

Sheet Calc_Chart3_Milestones
A1: Milestone | B1: Target Date | C1: Status | D1: Days Remaining
A2: Royal Assent | B2: ='Raw_Canada_Baseline'!B3 -> 2026-03-26 | C2: Complete | D2: =B2-TODAY() -> -114
A3: Phase 1/Read | B3: =DATE(VALUE('Raw_Canada_Baseline'!D4),1,1) -> 46023 | C3: Upcoming | D3: =B3-TODAY() -> -198
A4: Phase 2/Write-Payments | B4: =DATE(2027,7,1) -> 46569 | C4: Upcoming | D4: =B4-TODAY() -> 348

Sheet Calc_Chart4_Posture
A1: Bank | B1: Public Commitment Level (1-5) | C1: Digital Exposure Estimate (1-5)
A2: RBC | B2: 5 | C2: 5
A3: TD | B3: 5 | C3: 5
A4: BMO | B4: 5 | C4: 4
A5: CIBC | B5: 2 | C5: 3
A6: Scotiabank (BNS) | B6: 3 | C6: 3
A7: National Bank | B7: 3 | C7: 2
